flasksqlservice2/__init__.py
flasksqlservice2/__version__.py
flasksqlservice2/flasksqlservice.py
flasksqlservice2/model.py
flask_sqlservice2-1.0.5.dist-info/METADATA
flask_sqlservice2-1.0.5.dist-info/WHEEL
flask_sqlservice2-1.0.5.dist-info/top_level.txt
flask_sqlservice2-1.0.5.dist-info/RECORD
